pwstore/__init__.py
pwstore-0.1.dist-info/LICENSE
pwstore-0.1.dist-info/METADATA
pwstore-0.1.dist-info/WHEEL
pwstore-0.1.dist-info/entry_points.txt
pwstore-0.1.dist-info/top_level.txt
pwstore-0.1.dist-info/RECORD
