Metadata-Version: 2.1
Name: pwstore
Version: 0.1
Summary: a command-line password manager
Home-page: https://github.com/rpdelaney/pwstore
Author: Ryan Delaney
Author-email: ryan.delaney@gmail.com
License: GPL3
Keywords: security
Platform: UNKNOWN
Classifier: Development Status :: 4 - Beta
Classifier: Intended Audience :: End Users/Desktop
Classifier: License :: OSI Approved :: GNU General Public License v3 or later (GPLv3+)
Classifier: Programming Language :: Python :: 3
Classifier: Programming Language :: Python :: 3.3
Classifier: Programming Language :: Python :: 3.4
Classifier: Programming Language :: Python :: 3.5
Classifier: Programming Language :: Python :: 3.6
Classifier: Programming Language :: Python :: 3.7
Requires-Dist: python-gnupg
Requires-Dist: dulwich
Requires-Dist: Click
Requires-Dist: appdirs
Requires-Dist: PyQRCode
Requires-Dist: Pillow
Requires-Dist: pypng
Requires-Dist: pyperclip
Requires-Dist: PyAutoGUI
Provides-Extra: test
Requires-Dist: os; extra == 'test'
Requires-Dist: shutil; extra == 'test'
Requires-Dist: json; extra == 'test'
Requires-Dist: unittest; extra == 'test'
Requires-Dist: mock; extra == 'test'
Requires-Dist: tempfile; extra == 'test'
